{"homeHero2":{"url":"/uploads/image-1751087050993-618305055.jpg","originalName":"image6.jpg","size":345272,"mimetype":"image/jpeg","uploadedAt":"2025-06-28T05:04:11.039Z"},"homeHero1":{"url":"/uploads/image-1751694802939-859810964.svg","originalName":"11669400_20945431 (1).svg","size":165893,"mimetype":"image/svg+xml","uploadedAt":"2025-07-05T05:53:22.945Z"},"homeHero18":{"url":"/uploads/image-1751173122264-834835708.jpg","originalName":"image5.jpg","size":241840,"mimetype":"image/jpeg","uploadedAt":"2025-06-29T04:58:42.272Z"},"portfolioImage1":{"url":"/uploads/image-1751177568043-986925517.jpg","originalName":"image5.jpg","size":241840,"mimetype":"image/jpeg","uploadedAt":"2025-06-29T06:12:48.056Z"},"family01":{"url":"/uploads/image-1751177631272-462441846.jpg","originalName":"image5.jpg","size":241840,"mimetype":"image/jpeg","uploadedAt":"2025-06-29T06:13:51.571Z"},"portfolioImage2":{"url":"/uploads/image-1751694814343-477531065.svg","originalName":"37455480_8459336.svg","size":86058,"mimetype":"image/svg+xml","uploadedAt":"2025-07-05T05:53:34.348Z"},"p1":{"url":"/uploads/image-1751695036060-425282623.png","originalName":"6303a644ab1b900654aad3cb.png","size":3941,"mimetype":"image/png","uploadedAt":"2025-07-05T05:57:16.064Z"}}